schemainspect2/__init__.py
schemainspect2/command.py
schemainspect2/get.py
schemainspect2/graphlib/__init__.py
schemainspect2/inspected.py
schemainspect2/inspector.py
schemainspect2/misc.py
schemainspect2/pg/__init__.py
schemainspect2/pg/obj.py
schemainspect2/pg/sql/collations.sql
schemainspect2/pg/sql/collations9.sql
schemainspect2/pg/sql/constraints.sql
schemainspect2/pg/sql/deps.sql
schemainspect2/pg/sql/domains.sql
schemainspect2/pg/sql/enums.sql
schemainspect2/pg/sql/extensions.sql
schemainspect2/pg/sql/functions.sql
schemainspect2/pg/sql/indexes.sql
schemainspect2/pg/sql/privileges.sql
schemainspect2/pg/sql/relations.sql
schemainspect2/pg/sql/relations9.sql
schemainspect2/pg/sql/rlspolicies.sql
schemainspect2/pg/sql/schemas.sql
schemainspect2/pg/sql/sequences.sql
schemainspect2/pg/sql/triggers.sql
schemainspect2/pg/sql/types.sql
schemainspect2/tableformat.py
schemainspect2-0.1.dist-info/LICENSE
schemainspect2-0.1.dist-info/METADATA
schemainspect2-0.1.dist-info/WHEEL
schemainspect2-0.1.dist-info/entry_points.txt
schemainspect2-0.1.dist-info/RECORD
