Metadata-Version: 2.1
Name: schemainspect2
Version: 0.1
Summary: Schema inspection for PostgreSQL (and possibly others)
Home-page: https://github.com/anarkrypto/schemainspect
License: Unlicense
Author: Robert Lechte
Author-email: robertlechte@gmail.com
Requires-Python: >=3.7,<4
Classifier: License :: OSI Approved
Classifier: Programming Language :: Python :: 3
Classifier: Programming Language :: Python :: 3.7
Classifier: Programming Language :: Python :: 3.8
Classifier: Programming Language :: Python :: 3.9
Classifier: Programming Language :: Python :: 3.10
Classifier: Programming Language :: Python :: 3.11
Classifier: Programming Language :: Python :: 3.12
Requires-Dist: sqlalchemy
Project-URL: Repository, https://github.com/anarkrypto/schemainspect
